{
  "$schema": "https://ui.shadcn.com/schema/registry-item.json",
  "name": "apple-glass-effect-demo",
  "type": "registry:example",
  "title": "Apple Glass Effect Demo",
  "description": "Example showing an Apple Glass Effect.",
  "dependencies": ["..", "lucide-react"],
  "registryDependencies": ["https://nyxui.com/r/apple-glass-effect.json"],
  "files": [
    {
      "path": "registry/example/apple-glass-effect-demo.tsx",
      "content": "\"use client\";\nimport { useState } from \"react\";\nimport { GlassContainer } from \"../ui/apple-glass-effect\";\nimport {\n  Play,\n  Pause,\n  SkipBack,\n  SkipForward,\n  Volume2,\n  Heart,\n  Search,\n  Calendar,\n  Sun,\n  Wifi,\n  Battery,\n  Bluetooth,\n  AirVent,\n  Flashlight,\n  Calculator,\n  MessagesSquareIcon as Messages,\n  Bell,\n} from \"lucide-react\";\nimport Image from \"next/image\";\n\nexport const GlassExamples = () => {\n  const [isPlaying, setIsPlaying] = useState(false);\n  const [searchQuery, setSearchQuery] = useState(\"\");\n  const volume = 75;\n\n  return (\n    <div className=\"min-h-screen py-8 px-2 2xl:p-8\">\n      {/* Background */}\n      <div className=\"absolute inset-0\">\n        <Image\n          src=\"/assets/images/apple-glass-effect/img.jpg\"\n          alt=\"background image\"\n          fill\n          priority\n          className=\"h-full w-full object-cover absolute inset-0\"\n        />\n        <div className=\"absolute inset-0 bg-gradient-to-br from-blue-900/20 via-purple-900/30 to-pink-900/20\" />\n      </div>\n\n      <div className=\"max-w-7xl mx-auto relative z-10\">\n        {/* Top Row - Control Center Style */}\n        <div className=\"grid grid-cols-1 xl:grid-cols-3 gap-6 mb-8\">\n          {/* Music Player Widget */}\n          <GlassContainer\n            blur={0}\n            highlightOpacity={0}\n            innerGlowOpacity={0}\n            specularIntensity={0.5}\n            className=\"lg:col-span-2 h-58 w-full px-6\"\n          >\n            <div className=\"w-full\">\n              <div className=\"flex items-center gap-4 mb-4\">\n                <div className=\"w-16 h-16 bg-gradient-to-br from-pink-500 to-purple-600 rounded-xl flex items-center justify-center\">\n                  <Image\n                    src=\"/assets/images/apple-glass-effect/cover.jpeg\"\n                    alt=\"Music Cover\"\n                    width={64}\n                    height={64}\n                    className=\"rounded-lg shadow-lg\"\n                  />\n                </div>\n                <div className=\"flex-1\">\n                  <h3 className=\"text-md sm:text-lg font-semibold text-white\">\n                    Now Playing\n                  </h3>\n                  <p className=\"text-white/80 text-sm sm:text-base\">\n                    Until I Found You\n                  </p>\n                  <p className=\"text-white/60 text-sm\">Stephen Sanchez</p>\n                </div>\n                <Heart className=\"w-6 h-6 text-white/60 hover:text-red-400 cursor-pointer transition-colors hidden sm:block\" />\n              </div>\n\n              <div className=\"flex items-center justify-center gap-6 mb-4\">\n                <SkipBack className=\"w-5 h-5 sm:w-6 sm:h-6 text-white/80 hover:text-white cursor-pointer transition-colors\" />\n                <button\n                  onClick={() => setIsPlaying(!isPlaying)}\n                  className=\"w-12 h-12 bg-white/20 rounded-full flex items-center justify-center hover:bg-white/30 transition-colors\"\n                >\n                  {isPlaying ? (\n                    <Pause className=\"w-5 h-5 sm:w-6 sm:h-6 text-white\" />\n                  ) : (\n                    <Play className=\"w-5 h-5 sm:w-6 sm:h-6 text-white ml-1\" />\n                  )}\n                </button>\n                <SkipForward className=\"w-5 h-5 sm:w-6 sm:h-6 text-white/80 hover:text-white cursor-pointer transition-colors\" />\n              </div>\n\n              <div className=\"flex items-center gap-3\">\n                <Volume2 className=\"w-4 h-4 text-white/60\" />\n                <div className=\"flex-1 h-1 bg-white/20 rounded-full overflow-hidden\">\n                  <div\n                    className=\"h-full bg-white rounded-full transition-all duration-200\"\n                    style={{ width: `${volume}%` }}\n                  />\n                </div>\n                <span className=\"text-xs text-white/60 w-8\">{volume}%</span>\n              </div>\n\n              <div className=\"text-xs text-white/40 mt-3\">\n                Settings: Blur 0px • Highlight 0 • Glow 0 • Specular 0.5\n              </div>\n            </div>\n          </GlassContainer>\n\n          {/* Control Center Toggles */}\n          <GlassContainer\n            blur={20}\n            highlightOpacity={0.3}\n            innerGlowOpacity={0.2}\n            specularIntensity={0.4}\n            className=\"h-68\"\n          >\n            <div className=\"w-full\">\n              <h3 className=\"text-lg font-semibold text-white mb-4\">\n                Control Center\n              </h3>\n              <div className=\"grid grid-cols-2 gap-3\">\n                <div className=\"bg-blue-500/30 rounded-xl p-3 flex flex-col items-center gap-2 hover:bg-blue-500/40 transition-colors cursor-pointer\">\n                  <Wifi className=\"w-6 h-6 text-blue-300\" />\n                  <span className=\"text-xs text-white/80\">Wi-Fi</span>\n                </div>\n                <div className=\"bg-blue-500/30 rounded-xl p-3 flex flex-col items-center gap-2 hover:bg-blue-500/40 transition-colors cursor-pointer\">\n                  <Bluetooth className=\"w-6 h-6 text-blue-300\" />\n                  <span className=\"text-xs text-white/80\">Bluetooth</span>\n                </div>\n                <div className=\"bg-white/20 rounded-xl p-3 flex flex-col items-center gap-2 hover:bg-white/30 transition-colors cursor-pointer\">\n                  <AirVent className=\"w-6 h-6 text-white/80\" />\n                  <span className=\"text-xs text-white/80\">AirDrop</span>\n                </div>\n                <div className=\"bg-yellow-500/30 rounded-xl p-3 flex flex-col items-center gap-2 hover:bg-yellow-500/40 transition-colors cursor-pointer\">\n                  <Flashlight className=\"w-6 h-6 text-yellow-300\" />\n                  <span className=\"text-xs text-white/80\">Flashlight</span>\n                </div>\n              </div>\n              <div className=\"text-xs text-white/40 mt-3\">\n                Settings: Blur 20px • Highlight 0.3 • Glow 0.2 • Specular 0.4\n              </div>\n            </div>\n          </GlassContainer>\n        </div>\n\n        {/* Middle Row - Widgets */}\n        <div className=\"grid grid-cols-1 md:grid-cols-2 xl:grid-cols-4 gap-6 mb-8\">\n          {/* Weather Widget */}\n          <GlassContainer\n            blur={15}\n            highlightOpacity={0.5}\n            innerGlowOpacity={0.4}\n            specularIntensity={0.6}\n            className=\"h-44\"\n          >\n            <div className=\"w-full text-center\">\n              <div className=\"flex items-center justify-center mb-2\">\n                <Sun className=\"w-8 h-8 text-yellow-300\" />\n              </div>\n              <h3 className=\"text-2xl font-bold text-white mb-1\">72°</h3>\n              <p className=\"text-white/80 text-sm mb-1\">Sunny</p>\n              <p className=\"text-white/60 text-xs\">San Francisco</p>\n              <div className=\"text-xs text-white/40 mt-2\">\n                Blur 15px • Highlight 0.5\n              </div>\n            </div>\n          </GlassContainer>\n\n          {/* Calendar Widget */}\n          <GlassContainer\n            blur={3}\n            highlightOpacity={0.2}\n            innerGlowOpacity={0.1}\n            specularIntensity={0.3}\n            className=\"h-44\"\n          >\n            <div className=\"w-full\">\n              <div className=\"flex items-center gap-3 mb-3\">\n                <Calendar className=\"w-6 h-6 text-red-400\" />\n                <h3 className=\"text-lg font-semibold text-white\">Today</h3>\n              </div>\n              <div className=\"space-y-2\">\n                <div className=\"flex items-center gap-2\">\n                  <div className=\"w-2 h-2 bg-blue-400 rounded-full\"></div>\n                  <span className=\"text-sm text-white/80\">Team Meeting</span>\n                </div>\n                <div className=\"flex items-center gap-2\">\n                  <div className=\"w-2 h-2 bg-green-400 rounded-full\"></div>\n                  <span className=\"text-sm text-white/80\">Lunch Break</span>\n                </div>\n              </div>\n              <div className=\"text-xs text-white/40 mt-2\">\n                Blur 3px • Highlight 0.2\n              </div>\n            </div>\n          </GlassContainer>\n\n          {/* Notification Panel */}\n          <GlassContainer\n            blur={5}\n            highlightOpacity={0.6}\n            innerGlowOpacity={0.5}\n            specularIntensity={0.7}\n            className=\"h-44\"\n          >\n            <div className=\"w-full\">\n              <div className=\"flex items-center gap-3 mb-3\">\n                <Bell className=\"w-6 h-6 text-white\" />\n                <h3 className=\"text-lg font-semibold text-white\">\n                  Notifications\n                </h3>\n              </div>\n              <div className=\"space-y-2\">\n                <div className=\"flex items-center gap-3\">\n                  <div className=\"w-8 h-8 bg-blue-500 rounded-lg flex items-center justify-center\">\n                    <Messages className=\"w-4 h-4 text-white\" />\n                  </div>\n                  <div>\n                    <p className=\"text-sm text-white/90\">New message</p>\n                    <p className=\"text-xs text-white/60\">2 min ago</p>\n                  </div>\n                </div>\n              </div>\n              <div className=\"text-xs text-white/40 mt-2\">\n                Blur 5px • Highlight 0.6\n              </div>\n            </div>\n          </GlassContainer>\n\n          {/* Spotlight Search */}\n          <GlassContainer\n            blur={40}\n            highlightOpacity={0.8}\n            innerGlowOpacity={0.6}\n            specularIntensity={0.8}\n            className=\"h-44\"\n          >\n            <div className=\"w-full\">\n              <div className=\"flex items-center gap-3 mb-4\">\n                <Search className=\"w-6 h-6 text-white/80\" />\n                <input\n                  type=\"text\"\n                  placeholder=\"Spotlight Search\"\n                  value={searchQuery}\n                  onChange={(e) => setSearchQuery(e.target.value)}\n                  className=\"flex-1 bg-transparent text-white placeholder-white/60 outline-none\"\n                />\n              </div>\n              <div className=\"space-y-2\">\n                <div className=\"flex items-center gap-3 hover:bg-white/10 rounded-lg p-2 cursor-pointer transition-colors\">\n                  <Calculator className=\"w-5 h-5 text-white/80\" />\n                  <span className=\"text-sm text-white/80\">Calculator</span>\n                </div>\n              </div>\n              <div className=\"text-xs text-white/40 mt-2\">\n                Blur 40px • Highlight 0.8\n              </div>\n            </div>\n          </GlassContainer>\n        </div>\n\n        {/* Dock */}\n        <GlassContainer\n          blur={0}\n          highlightOpacity={0.3}\n          innerGlowOpacity={0.2}\n          specularIntensity={0.4}\n          className=\"mx-auto max-w-[39rem] h-32 rounded-2xl hidden md:block\"\n        >\n          <div className=\"w-full flex items-center justify-center\">\n            <div className=\"flex items-center gap-4\">\n              {[\n                {\n                  src: \"/assets/images/apple-glass-effect/finder.webp\",\n                  alt: \"finder\",\n                },\n                {\n                  src: \"/assets/images/apple-glass-effect/map.webp\",\n                  alt: \"maps\",\n                },\n                {\n                  src: \"/assets/images/apple-glass-effect/safari.webp\",\n                  alt: \"safari\",\n                },\n                {\n                  src: \"/assets/images/apple-glass-effect/books.webp\",\n                  alt: \"books\",\n                },\n                {\n                  src: \"/assets/images/apple-glass-effect/messages.webp\",\n                  alt: \"messages\",\n                },\n              ].map((app, index) => (\n                <div\n                  key={index}\n                  className={`w-24 h-24 rounded-xl flex items-center justify-center hover:scale-110 transition-transform cursor-pointer shadow-lg`}\n                >\n                  <Image\n                    src={app.src}\n                    alt={app.alt}\n                    width={500}\n                    height={500}\n                    quality={100}\n                  />\n                </div>\n              ))}\n            </div>\n          </div>\n        </GlassContainer>\n\n        {/* Settings Info */}\n        <div className=\"mt-8 text-center hidden md:block\">\n          <p className=\"text-white/60 text-sm\">\n            Dock Settings: Blur 0px • Highlight 0.3 • Glow 0.2 • Specular 0.4 •\n            Border Radius 2.5rem\n          </p>\n        </div>\n\n        {/* Menu Bar */}\n        <GlassContainer\n          blur={20}\n          highlightOpacity={0.4}\n          innerGlowOpacity={0.3}\n          specularIntensity={0.5}\n          className=\"fixed top-4 left-4 right-4 h-12 z-50 rounded-[1rem] hidden md:block\"\n        >\n          <div className=\"w-full flex items-center justify-between px-4\">\n            <div className=\"flex items-center gap-4\">\n              <span className=\"text-white/80 text-sm\">Finder</span>\n              <span className=\"text-white/80 text-sm\">File</span>\n              <span className=\"text-white/80 text-sm\">Edit</span>\n              <span className=\"text-white/80 text-sm\">View</span>\n            </div>\n            <div className=\"flex items-center gap-4\">\n              <Wifi className=\"w-4 h-4 text-white/80\" />\n              <Battery className=\"w-4 h-4 text-white/80\" />\n              <span className=\"text-white/80 text-sm\">2:30 PM</span>\n            </div>\n          </div>\n        </GlassContainer>\n      </div>\n\n      {/* Custom Slider Styles */}\n      <style jsx>{`\n        .slider::-webkit-slider-thumb {\n          appearance: none;\n          height: 16px;\n          width: 16px;\n          border-radius: 50%;\n          background: white;\n          cursor: pointer;\n          box-shadow: 0 2px 4px rgba(0, 0, 0, 0.2);\n        }\n\n        .slider::-moz-range-thumb {\n          height: 16px;\n          width: 16px;\n          border-radius: 50%;\n          background: white;\n          cursor: pointer;\n          border: none;\n          box-shadow: 0 2px 4px rgba(0, 0, 0, 0.2);\n        }\n      `}</style>\n    </div>\n  );\n};\n",
      "type": "registry:example",
      "target": "components/apple-glass-effect-demo.tsx"
    }
  ]
}
