{
  "$schema": "https://ui.shadcn.com/schema/registry-item.json",
  "name": "keyboard-demo1",
  "type": "registry:example",
  "title": "Keyboard Demo 1",
  "description": "Example showing a interactive keyboard.",
  "dependencies": [
    ".."
  ],
  "registryDependencies": [
    "https://nuvyxui.vercel.app/r/keyboard.json"
  ],
  "files": [
    {
      "path": "registry/example/keyboard-demo1.tsx",
      "content": "import React from \"react\";\nimport InteractiveKeyboard from \"../ui/keyboard\";\n\nexport default function KeyboardDemo1() {\n  return (\n    <div>\n      <InteractiveKeyboard theme=\"neon\" />\n    </div>\n  );\n}\n",
      "type": "registry:example",
      "target": "components/keyboard-demo1.tsx"
    },
    {
      "path": "registry\\example\\keyboard-demo1.tsx",
      "content": "import React from \"react\";\nimport InteractiveKeyboard from \"../ui/keyboard\";\n\nexport default function KeyboardDemo1() {\n  return (\n    <div>\n      <InteractiveKeyboard theme=\"neon\" />\n    </div>\n  );\n}\n",
      "type": "registry:component",
      "target": ""
    }
  ]
}