{
  "$schema": "https://ui.shadcn.com/schema/registry-item.json",
  "name": "water-ripple-effect-demo",
  "type": "registry:example",
  "title": "Water Ripple Effect Demo",
  "description": "Example showing a water ripple effect.",
  "dependencies": [".."],
  "registryDependencies": ["https://nyxui.com/r/water-ripple-effect.json"],
  "files": [
    {
      "path": "registry/example/water-ripple-effect-demo.tsx",
      "content": "import React from \"react\";\nimport WaterRippleEffect from \"../ui/water-ripple-effect\";\n\nexport default function WaterRippleEffectDemo() {\n  return (\n    <div>\n      <WaterRippleEffect\n        imageSrc=\"/assets/images/water-ripple-effect/art.jpg\"\n        height={620}\n        width={600}\n        /*        className='scale-50 md:scale-100' */\n      />\n    </div>\n  );\n}\n",
      "type": "registry:example",
      "target": "components/water-ripple-effect-demo.tsx"
    }
  ]
}
